wolframalpha/__init__.py
wolframalpha/pmxbot.py
wolframalpha-5.1.3.dist-info/LICENSE
wolframalpha-5.1.3.dist-info/METADATA
wolframalpha-5.1.3.dist-info/WHEEL
wolframalpha-5.1.3.dist-info/entry_points.txt
wolframalpha-5.1.3.dist-info/top_level.txt
wolframalpha-5.1.3.dist-info/RECORD
