Metadata-Version: 2.1
Name: wolframalpha
Version: 5.1.3
Summary: Wolfram|Alpha 2.0 API client
Author-email: "Jason R. Coombs" <jaraco@jaraco.com>
Project-URL: Homepage, https://github.com/jaraco/wolframalpha
Classifier: Development Status :: 5 - Production/Stable
Classifier: Intended Audience :: Developers
Classifier: License :: OSI Approved :: MIT License
Classifier: Programming Language :: Python :: 3
Classifier: Programming Language :: Python :: 3 :: Only
Requires-Python: >=3.8
License-File: LICENSE
Requires-Dist: xmltodict
Requires-Dist: more_itertools
Requires-Dist: jaraco.context
Requires-Dist: httpx
Requires-Dist: multidict
Provides-Extra: test
Requires-Dist: pytest!=8.1.*,>=6; extra == "test"
Requires-Dist: pytest-checkdocs>=2.4; extra == "test"
Requires-Dist: pytest-cov; extra == "test"
Requires-Dist: pytest-mypy; extra == "test"
Requires-Dist: pytest-enabler>=2.2; extra == "test"
Requires-Dist: pytest-ruff>=0.2.1; extra == "test"
Requires-Dist: pmxbot; extra == "test"
Requires-Dist: keyring; extra == "test"
Provides-Extra: doc
Requires-Dist: sphinx>=3.5; extra == "doc"
Requires-Dist: jaraco.packaging>=9.3; extra == "doc"
Requires-Dist: rst.linker>=1.9; extra == "doc"
Requires-Dist: furo; extra == "doc"
Requires-Dist: sphinx-lint; extra == "doc"
